<?xml version="1.0" encoding="ISO-8859-1"?>
<?xml-stylesheet type="text/css" href="currency_table_widget.css"?>
<CATALOG>
<TIMESTAMP>Rates updated on 8/12/2021 at 13:45:10 </TIMESTAMP>

<RATE>
<ISFLAGGED>**</ISFLAGGED>
<FLAGURL>flags/USD.JPG</FLAGURL>
<ISO>USD</ISO>
<NAME>Dollars</NAME>
<COUNTRY>United States of America</COUNTRY>
<ID></ID>
<WEBUY>1.3599</WEBUY>
<WESELL>1.44671</WESELL>
<INVBUY>0.7353</INVBUY>
<INVSELL>0.6912</INVSELL>
</RATE>
<RATE>
<ISFLAGGED>**</ISFLAGGED>
<FLAGURL>flags/EUR.JPG</FLAGURL>
<ISO>EUR</ISO>
<NAME>Euro</NAME>
<COUNTRY>Euro Member Countries </COUNTRY>
<ID></ID>
<WEBUY>1.51672</WEBUY>
<WESELL>1.65051</WESELL>
<INVBUY>0.6593</INVBUY>
<INVSELL>0.6059</INVSELL>
</RATE>
<RATE>
<ISFLAGGED>**</ISFLAGGED>
<FLAGURL>flags/GBP.JPG</FLAGURL>
<ISO>GBP</ISO>
<NAME>Pounds</NAME>
<COUNTRY>United Kingdom</COUNTRY>
<ID></ID>
<WEBUY>1.77637</WEBUY>
<WESELL>1.9213</WESELL>
<INVBUY>0.5629</INVBUY>
<INVSELL>0.5205</INVSELL>
</RATE>
<RATE>
<ISFLAGGED>**</ISFLAGGED>
<FLAGURL>flags/NZD.JPG</FLAGURL>
<ISO>NZD</ISO>
<NAME>Dollars</NAME>
<COUNTRY>New Zealand</COUNTRY>
<ID></ID>
<WEBUY>0.914280072</WEBUY>
<WESELL>0.9924563</WESELL>
<INVBUY>1.09375675</INVBUY>
<INVSELL>1.00760104</INVSELL>
</RATE>
<RATE>
<ISFLAGGED>**</ISFLAGGED>
<FLAGURL>flags/CHF.JPG</FLAGURL>
<ISO>CHF</ISO>
<NAME>Francs</NAME>
<COUNTRY>Switzerland</COUNTRY>
<ID></ID>
<WEBUY>1.41031</WEBUY>
<WESELL>1.6043</WESELL>
<INVBUY>0.7091</INVBUY>
<INVSELL>0.6233</INVSELL>
</RATE>
<RATE>
<ISFLAGGED>**</ISFLAGGED>
<FLAGURL>flags/JPY.JPG</FLAGURL>
<ISO>JPY</ISO>
<NAME>Yen</NAME>
<COUNTRY>Japan</COUNTRY>
<ID></ID>
<WEBUY>0.011694</WEBUY>
<WESELL>0.012808</WESELL>
<INVBUY>85.5112</INVBUY>
<INVSELL>78.0756</INVSELL>
</RATE>
<RATE>
<ISFLAGGED>**</ISFLAGGED>
<FLAGURL>flags/CNY.JPG</FLAGURL>
<ISO>CNY</ISO>
<NAME>Yuan Renminbi</NAME>
<COUNTRY>China</COUNTRY>
<ID></ID>
<WEBUY>0.20571</WEBUY>
<WESELL>0.23604</WESELL>
<INVBUY>4.8612</INVBUY>
<INVSELL>4.2365</INVSELL>
</RATE>
<RATE>
<ISFLAGGED>**</ISFLAGGED>
<FLAGURL>flags/THB.JPG</FLAGURL>
<ISO>THB</ISO>
<NAME>Baht</NAME>
<COUNTRY>Thailand</COUNTRY>
<ID></ID>
<WEBUY>0.03865229</WEBUY>
<WESELL>0.0438538</WESELL>
<INVBUY>25.87168808</INVBUY>
<INVSELL>22.80304101</INVSELL>
</RATE>
<RATE>
<ISFLAGGED>**</ISFLAGGED>
<FLAGURL>flags/CAD.JPG</FLAGURL>
<ISO>CAD</ISO>
<NAME>Dollars</NAME>
<COUNTRY>Canada</COUNTRY>
<ID></ID>
<WEBUY>1.05966</WEBUY>
<WESELL>1.16361</WESELL>
<INVBUY>0.9437</INVBUY>
<INVSELL>0.8594</INVSELL>
</RATE>
<RATE>
<ISFLAGGED>**</ISFLAGGED>
<FLAGURL>flags/IDR.JPG</FLAGURL>
<ISO>IDR</ISO>
<NAME>Rupiahs</NAME>
<COUNTRY>Indonesia</COUNTRY>
<ID></ID>
<WEBUY>0.000089356</WEBUY>
<WESELL>0.0001072</WESELL>
<INVBUY>11191.194553255</INVBUY>
<INVSELL>9328.358208955</INVSELL>
</RATE>
<RATE>
<ISFLAGGED>*</ISFLAGGED>
<FLAGURL>flags/AED.JPG</FLAGURL>
<ISO>AED</ISO>
<NAME>Dirhams</NAME>
<COUNTRY>United Arab Emirates</COUNTRY>
<ID></ID>
<WEBUY>0.353</WEBUY>
<WESELL>0.4157</WESELL>
<INVBUY>2.8332</INVBUY>
<INVSELL>2.4058</INVSELL>
</RATE>
<RATE>
<ISFLAGGED>*</ISFLAGGED>
<FLAGURL>flags/ARS.JPG</FLAGURL>
<ISO>ARS</ISO>
<NAME>Pesos</NAME>
<COUNTRY>Argentina</COUNTRY>
<ID></ID>
<WEBUY>0.011637252</WEBUY>
<WESELL>0.0180793</WESELL>
<INVBUY>85.93093617</INVBUY>
<INVSELL>55.31187601</INVSELL>
</RATE>
<RATE>
<ISFLAGGED>*</ISFLAGGED>
<FLAGURL>flags/AUD.JPG</FLAGURL>
<ISO>AUD</ISO>
<NAME>Dollars</NAME>
<COUNTRY>Australia</COUNTRY>
<ID></ID>
<WEBUY>1</WEBUY>
<WESELL>1</WESELL>
<INVBUY>1</INVBUY>
<INVSELL>1</INVSELL>
</RATE>
<RATE>
<ISFLAGGED>*</ISFLAGGED>
<FLAGURL>flags/BND.JPG</FLAGURL>
<ISO>BND</ISO>
<NAME>Dollars</NAME>
<COUNTRY>Brunei Darussalam</COUNTRY>
<ID></ID>
<WEBUY>0.9435</WEBUY>
<WESELL>1.1466</WESELL>
<INVBUY>1.0599</INVBUY>
<INVSELL>0.8722</INVSELL>
</RATE>
<RATE>
<ISFLAGGED>*</ISFLAGGED>
<FLAGURL>flags/BRL.JPG</FLAGURL>
<ISO>BRL</ISO>
<NAME>Brazil Real</NAME>
<COUNTRY>Brazil</COUNTRY>
<ID></ID>
<WEBUY>0.2277</WEBUY>
<WESELL>0.2827</WESELL>
<INVBUY>4.3921</INVBUY>
<INVSELL>3.537</INVSELL>
</RATE>
<RATE>
<ISFLAGGED>*</ISFLAGGED>
<FLAGURL>flags/CLP.JPG</FLAGURL>
<ISO>CLP</ISO>
<NAME>Pesos</NAME>
<COUNTRY>Chile</COUNTRY>
<ID></ID>
<WEBUY>0.001504936</WEBUY>
<WESELL>0.0019063</WESELL>
<INVBUY>664.48012836</INVBUY>
<INVSELL>524.57640455</INVSELL>
</RATE>
<RATE>
<ISFLAGGED>*</ISFLAGGED>
<FLAGURL>flags/COP.JPG</FLAGURL>
<ISO>COP</ISO>
<NAME>Pesos</NAME>
<COUNTRY>Colombia</COUNTRY>
<ID></ID>
<WEBUY>0.000322588</WEBUY>
<WESELL>0.0004102</WESELL>
<INVBUY>3099.93247355</INVBUY>
<INVSELL>2437.83520234</INVSELL>
</RATE>
<RATE>
<ISFLAGGED>*</ISFLAGGED>
<FLAGURL>flags/CZK.JPG</FLAGURL>
<ISO>CZK</ISO>
<NAME>Koruny</NAME>
<COUNTRY>Czech Republic</COUNTRY>
<ID></ID>
<WEBUY>0.056233013</WEBUY>
<WESELL>0.0694826</WESELL>
<INVBUY>17.78314824</INVBUY>
<INVSELL>14.39209241</INVSELL>
</RATE>
<RATE>
<ISFLAGGED>*</ISFLAGGED>
<FLAGURL>flags/DKK.JPG</FLAGURL>
<ISO>DKK</ISO>
<NAME>Kroner</NAME>
<COUNTRY>Denmark</COUNTRY>
<ID></ID>
<WEBUY>0.19639</WEBUY>
<WESELL>0.2302</WESELL>
<INVBUY>5.0919</INVBUY>
<INVSELL>4.344</INVSELL>
</RATE>
<RATE>
<ISFLAGGED>*</ISFLAGGED>
<FLAGURL>flags/EGP.JPG</FLAGURL>
<ISO>EGP</ISO>
<NAME>Pounds</NAME>
<COUNTRY>Egypt</COUNTRY>
<ID></ID>
<WEBUY>0.07989</WEBUY>
<WESELL>0.103</WESELL>
<INVBUY>12.5176</INVBUY>
<INVSELL>9.7087</INVSELL>
</RATE>
<RATE>
<ISFLAGGED>*</ISFLAGGED>
<FLAGURL>flags/FJD.JPG</FLAGURL>
<ISO>FJD</ISO>
<NAME>Dollars</NAME>
<COUNTRY>Fiji</COUNTRY>
<ID></ID>
<WEBUY>0.606595148</WEBUY>
<WESELL>0.7079686</WESELL>
<INVBUY>1.64854599</INVBUY>
<INVSELL>1.41249202</INVSELL>
</RATE>
<RATE>
<ISFLAGGED>*</ISFLAGGED>
<FLAGURL>flags/HKD.JPG</FLAGURL>
<ISO>HKD</ISO>
<NAME>Dollars</NAME>
<COUNTRY>Hong Kong</COUNTRY>
<ID></ID>
<WEBUY>0.166865676</WEBUY>
<WESELL>0.1891064</WESELL>
<INVBUY>5.99284421</INVBUY>
<INVSELL>5.28802833</INVSELL>
</RATE>
<RATE>
<ISFLAGGED>*</ISFLAGGED>
<FLAGURL>flags/HRK.JPG</FLAGURL>
<ISO>HRK</ISO>
<NAME>Kuna</NAME>
<COUNTRY>Croatia</COUNTRY>
<ID></ID>
<WEBUY>0.19051</WEBUY>
<WESELL>0.23511</WESELL>
<INVBUY>5.2491</INVBUY>
<INVSELL>4.2533</INVSELL>
</RATE>
<RATE>
<ISFLAGGED>*</ISFLAGGED>
<FLAGURL>flags/HUF.JPG</FLAGURL>
<ISO>HUF</ISO>
<NAME>Forint</NAME>
<COUNTRY>Hungary</COUNTRY>
<ID></ID>
<WEBUY>0.003895865</WEBUY>
<WESELL>0.0048696</WESELL>
<INVBUY>256.68241777</INVBUY>
<INVSELL>205.35567603</INVSELL>
</RATE>
<RATE>
<ISFLAGGED>*</ISFLAGGED>
<FLAGURL>flags/ILS.JPG</FLAGURL>
<ISO>ILS</ISO>
<NAME>New Shekels</NAME>
<COUNTRY>Israel</COUNTRY>
<ID></ID>
<WEBUY>0.408388472</WEBUY>
<WESELL>0.502632</WESELL>
<INVBUY>2.44864894</INVBUY>
<INVSELL>1.98952713</INVSELL>
</RATE>
<RATE>
<ISFLAGGED>*</ISFLAGGED>
<FLAGURL>flags/INR.JPG</FLAGURL>
<ISO>INR</ISO>
<NAME>Rupees</NAME>
<COUNTRY>India</COUNTRY>
<ID></ID>
<WEBUY>0.01708</WEBUY>
<WESELL>0.02094</WESELL>
<INVBUY>58.5348</INVBUY>
<INVSELL>47.7596</INVSELL>
</RATE>
<RATE>
<ISFLAGGED>*</ISFLAGGED>
<FLAGURL>flags/ISK.JPG</FLAGURL>
<ISO>ISK</ISO>
<NAME>Kronur</NAME>
<COUNTRY>Iceland</COUNTRY>
<ID></ID>
<WEBUY>0.009485759</WEBUY>
<WESELL>0.0123143</WESELL>
<INVBUY>105.42118783</INVBUY>
<INVSELL>81.20640231</INVSELL>
</RATE>
<RATE>
<ISFLAGGED>*</ISFLAGGED>
<FLAGURL>flags/JOD.JPG</FLAGURL>
<ISO>JOD</ISO>
<NAME>Dinars</NAME>
<COUNTRY>Jordan</COUNTRY>
<ID></ID>
<WEBUY>1.791242497</WEBUY>
<WESELL>2.2311273</WESELL>
<INVBUY>0.5582717</INVBUY>
<INVSELL>0.44820392</INVSELL>
</RATE>
<RATE>
<ISFLAGGED>*</ISFLAGGED>
<FLAGURL>flags/KRW.JPG</FLAGURL>
<ISO>KRW</ISO>
<NAME>Won</NAME>
<COUNTRY>Korea (South)</COUNTRY>
<ID></ID>
<WEBUY>0.001080028</WEBUY>
<WESELL>0.0013247</WESELL>
<INVBUY>925.9020025</INVBUY>
<INVSELL>754.88789915</INVSELL>
</RATE>
<RATE>
<ISFLAGGED>*</ISFLAGGED>
<FLAGURL>flags/KWD.JPG</FLAGURL>
<ISO>KWD</ISO>
<NAME>Dinars</NAME>
<COUNTRY>Kuwait</COUNTRY>
<ID></ID>
<WEBUY>4.267441668</WEBUY>
<WESELL>5.1023759</WESELL>
<INVBUY>0.23433244</INVBUY>
<INVSELL>0.19598713</INVSELL>
</RATE>
<RATE>
<ISFLAGGED>*</ISFLAGGED>
<FLAGURL>flags/LKR.JPG</FLAGURL>
<ISO>LKR</ISO>
<NAME>Rupees</NAME>
<COUNTRY>Sri Lanka</COUNTRY>
<ID></ID>
<WEBUY>0.006195545</WEBUY>
<WESELL>0.0083086</WESELL>
<INVBUY>161.40631292</INVBUY>
<INVSELL>120.35722023</INVSELL>
</RATE>
<RATE>
<ISFLAGGED>*</ISFLAGGED>
<FLAGURL>flags/MAD.JPG</FLAGURL>
<ISO>MAD</ISO>
<NAME>Dirhams</NAME>
<COUNTRY>Morocco</COUNTRY>
<ID></ID>
<WEBUY>0.13466</WEBUY>
<WESELL>0.18087</WESELL>
<INVBUY>7.4259</INVBUY>
<INVSELL>5.5289</INVSELL>
</RATE>
<RATE>
<ISFLAGGED>*</ISFLAGGED>
<FLAGURL>flags/MUR.JPG</FLAGURL>
<ISO>MUR</ISO>
<NAME>Rupees</NAME>
<COUNTRY>Mauritius</COUNTRY>
<ID></ID>
<WEBUY>0.027156938</WEBUY>
<WESELL>0.0385923</WESELL>
<INVBUY>36.82300199</INVBUY>
<INVSELL>25.91190471</INVSELL>
</RATE>
<RATE>
<ISFLAGGED>*</ISFLAGGED>
<FLAGURL>flags/MXN.JPG</FLAGURL>
<ISO>MXN</ISO>
<NAME>Pesos</NAME>
<COUNTRY>Mexico</COUNTRY>
<ID></ID>
<WEBUY>0.05978</WEBUY>
<WESELL>0.0748</WESELL>
<INVBUY>16.7288</INVBUY>
<INVSELL>13.3681</INVSELL>
</RATE>
<RATE>
<ISFLAGGED>*</ISFLAGGED>
<FLAGURL>flags/MYR.JPG</FLAGURL>
<ISO>MYR</ISO>
<NAME>Ringgits</NAME>
<COUNTRY>Malaysia</COUNTRY>
<ID></ID>
<WEBUY>0.305355364</WEBUY>
<WESELL>0.3578808</WESELL>
<INVBUY>3.27487288</INVBUY>
<INVSELL>2.79422646</INVSELL>
</RATE>
<RATE>
<ISFLAGGED>*</ISFLAGGED>
<FLAGURL>flags/NOK.JPG</FLAGURL>
<ISO>NOK</ISO>
<NAME>Krone</NAME>
<COUNTRY>Norway</COUNTRY>
<ID></ID>
<WEBUY>0.1429</WEBUY>
<WESELL>0.16899</WESELL>
<INVBUY>6.9979</INVBUY>
<INVSELL>5.9176</INVSELL>
</RATE>
<RATE>
<ISFLAGGED>*</ISFLAGGED>
<FLAGURL>flags/NPR.JPG</FLAGURL>
<ISO>NPR</ISO>
<NAME>Nepal Rupees</NAME>
<COUNTRY>Nepal</COUNTRY>
<ID></ID>
<WEBUY>0.009779079</WEBUY>
<WESELL>0.0146977</WESELL>
<INVBUY>102.25911617</INVBUY>
<INVSELL>68.03785626</INVSELL>
</RATE>
<RATE>
<ISFLAGGED>*</ISFLAGGED>
<FLAGURL>flags/OMR.JPG</FLAGURL>
<ISO>OMR</ISO>
<NAME>Rials</NAME>
<COUNTRY>Oman</COUNTRY>
<ID></ID>
<WEBUY>3.3025</WEBUY>
<WESELL>4.0287</WESELL>
<INVBUY>0.3028</INVBUY>
<INVSELL>0.2482</INVSELL>
</RATE>
<RATE>
<ISFLAGGED>*</ISFLAGGED>
<FLAGURL>flags/PGK.JPG</FLAGURL>
<ISO>PGK</ISO>
<NAME>Kina</NAME>
<COUNTRY>Papua New Guinea</COUNTRY>
<ID></ID>
<WEBUY>0.3305</WEBUY>
<WESELL>0.4749</WESELL>
<INVBUY>3.0256</INVBUY>
<INVSELL>2.1056</INVSELL>
</RATE>
<RATE>
<ISFLAGGED>*</ISFLAGGED>
<FLAGURL>flags/PHP.JPG</FLAGURL>
<ISO>PHP</ISO>
<NAME>Pesos</NAME>
<COUNTRY>Philippines</COUNTRY>
<ID></ID>
<WEBUY>0.024515228</WEBUY>
<WESELL>0.0312189</WESELL>
<INVBUY>40.7909731</INVBUY>
<INVSELL>32.03187813</INVSELL>
</RATE>
<RATE>
<ISFLAGGED>*</ISFLAGGED>
<FLAGURL>flags/PLN.JPG</FLAGURL>
<ISO>PLN</ISO>
<NAME>Zlotych</NAME>
<COUNTRY>Poland</COUNTRY>
<ID></ID>
<WEBUY>0.3143</WEBUY>
<WESELL>0.3868</WESELL>
<INVBUY>3.1815</INVBUY>
<INVSELL>2.585</INVSELL>
</RATE>
<RATE>
<ISFLAGGED>*</ISFLAGGED>
<FLAGURL>flags/QAR.JPG</FLAGURL>
<ISO>QAR</ISO>
<NAME>Rials</NAME>
<COUNTRY>Qatar</COUNTRY>
<ID></ID>
<WEBUY>0.34951</WEBUY>
<WESELL>0.42482</WESELL>
<INVBUY>2.8611</INVBUY>
<INVSELL>2.3539</INVSELL>
</RATE>
<RATE>
<ISFLAGGED>*</ISFLAGGED>
<FLAGURL>flags/RUR.JPG</FLAGURL>
<ISO>RUR</ISO>
<NAME>Rubles</NAME>
<COUNTRY>Russia</COUNTRY>
<ID></ID>
<WEBUY>0.01677</WEBUY>
<WESELL>0.02115</WESELL>
<INVBUY>59.6321</INVBUY>
<INVSELL>47.2777</INVSELL>
</RATE>
<RATE>
<ISFLAGGED>*</ISFLAGGED>
<FLAGURL>flags/SAR.JPG</FLAGURL>
<ISO>SAR</ISO>
<NAME>Riyals</NAME>
<COUNTRY>Saudi Arabia</COUNTRY>
<ID></ID>
<WEBUY>0.33324</WEBUY>
<WESELL>0.41936</WESELL>
<INVBUY>3.0008</INVBUY>
<INVSELL>2.3846</INVSELL>
</RATE>
<RATE>
<ISFLAGGED>*</ISFLAGGED>
<FLAGURL>flags/SBD.JPG</FLAGURL>
<ISO>SBD</ISO>
<NAME>Dollars</NAME>
<COUNTRY>Solomon Islands</COUNTRY>
<ID></ID>
<WEBUY>0.1469</WEBUY>
<WESELL>0.1984</WESELL>
<INVBUY>6.8094</INVBUY>
<INVSELL>5.0413</INVSELL>
</RATE>
<RATE>
<ISFLAGGED>*</ISFLAGGED>
<FLAGURL>flags/SEK.JPG</FLAGURL>
<ISO>SEK</ISO>
<NAME>Kronor</NAME>
<COUNTRY>Sweden</COUNTRY>
<ID></ID>
<WEBUY>0.143114939</WEBUY>
<WESELL>0.1671218</WESELL>
<INVBUY>6.98739072</INVBUY>
<INVSELL>5.98365982</INVSELL>
</RATE>
<RATE>
<ISFLAGGED>*</ISFLAGGED>
<FLAGURL>flags/SGD.JPG</FLAGURL>
<ISO>SGD</ISO>
<NAME>Dollars</NAME>
<COUNTRY>Singapore</COUNTRY>
<ID></ID>
<WEBUY>0.9589</WEBUY>
<WESELL>1.07973</WESELL>
<INVBUY>1.0429</INVBUY>
<INVSELL>0.9262</INVSELL>
</RATE>
<RATE>
<ISFLAGGED>*</ISFLAGGED>
<FLAGURL>flags/TOP.JPG</FLAGURL>
<ISO>TOP</ISO>
<NAME>Pa'anga</NAME>
<COUNTRY>Tonga</COUNTRY>
<ID></ID>
<WEBUY>0.5329</WEBUY>
<WESELL>0.7044</WESELL>
<INVBUY>1.8766</INVBUY>
<INVSELL>1.4197</INVSELL>
</RATE>
<RATE>
<ISFLAGGED>*</ISFLAGGED>
<FLAGURL>flags/TRL.JPG</FLAGURL>
<ISO>TRL</ISO>
<NAME>Liras</NAME>
<COUNTRY>Turkey</COUNTRY>
<ID></ID>
<WEBUY>0.0939</WEBUY>
<WESELL>0.1164</WESELL>
<INVBUY>10.6467</INVBUY>
<INVSELL>8.5896</INVSELL>
</RATE>
<RATE>
<ISFLAGGED>*</ISFLAGGED>
<FLAGURL>flags/TWD.JPG</FLAGURL>
<ISO>TWD</ISO>
<NAME>New Dollars</NAME>
<COUNTRY>Taiwan</COUNTRY>
<ID></ID>
<WEBUY>0.0457</WEBUY>
<WESELL>0.0567</WESELL>
<INVBUY>21.8984</INVBUY>
<INVSELL>17.65</INVSELL>
</RATE>
<RATE>
<ISFLAGGED>*</ISFLAGGED>
<FLAGURL>flags/VND.JPG</FLAGURL>
<ISO>VND</ISO>
<NAME>Dong</NAME>
<COUNTRY>Viet Nam</COUNTRY>
<ID></ID>
<WEBUY>0.000053322</WEBUY>
<WESELL>0.0000705</WESELL>
<INVBUY>18753.94301652</INVBUY>
<INVSELL>14184.39716312</INVSELL>
</RATE>
<RATE>
<ISFLAGGED>*</ISFLAGGED>
<FLAGURL>flags/VUV.JPG</FLAGURL>
<ISO>VUV</ISO>
<NAME>Vatu</NAME>
<COUNTRY>Vanuatu</COUNTRY>
<ID></ID>
<WEBUY>0.011263304</WEBUY>
<WESELL>0.0138625</WESELL>
<INVBUY>88.78389605</INVBUY>
<INVSELL>72.13706041</INVSELL>
</RATE>
<RATE>
<ISFLAGGED>*</ISFLAGGED>
<FLAGURL>flags/WST.JPG</FLAGURL>
<ISO>WST</ISO>
<NAME>Tala</NAME>
<COUNTRY>Samoa</COUNTRY>
<ID></ID>
<WEBUY>0.47942151</WEBUY>
<WESELL>0.6104747</WESELL>
<INVBUY>2.08584717</INVBUY>
<INVSELL>1.63806952</INVSELL>
</RATE>
<RATE>
<ISFLAGGED>*</ISFLAGGED>
<FLAGURL>flags/XPF.JPG</FLAGURL>
<ISO>XPF</ISO>
<NAME></NAME>
<COUNTRY>Comptoirs Français du Pacifiqu</COUNTRY>
<ID></ID>
<WEBUY>0.011938289</WEBUY>
<WESELL>0.0146674</WESELL>
<INVBUY>83.76410018</INVBUY>
<INVSELL>68.17840926</INVSELL>
</RATE>
<RATE>
<ISFLAGGED>*</ISFLAGGED>
<FLAGURL>flags/ZAR.JPG</FLAGURL>
<ISO>ZAR</ISO>
<NAME>Rand</NAME>
<COUNTRY>South Africa</COUNTRY>
<ID></ID>
<WEBUY>0.081713793</WEBUY>
<WESELL>0.0949647</WESELL>
<INVBUY>12.23783598</INVBUY>
<INVSELL>10.5302286</INVSELL>
</RATE>
</CATALOG>
