<?xml version="1.0" encoding="ISO-8859-1"?>
<?xml-stylesheet type="text/css" href="currency_table_widget.css"?>
<CATALOG>
<TIMESTAMP>Rates updated on 6/07/2021 at 15:52:28 UTC+10</TIMESTAMP>

<RATE>
<ISFLAGGED>*</ISFLAGGED>
<FLAGURL>flags/USD.JPG</FLAGURL>
<ISO>USD</ISO>
<NAME>Dollars</NAME>
<COUNTRY>United States of America</COUNTRY>
<WEBUY>1.19717</WEBUY>
<WESELL>1.34048</WESELL>
<INVBUY>0.8353</INVBUY>
<INVSELL>0.746</INVSELL>
</RATE>
<RATE>
<ISFLAGGED>*</ISFLAGGED>
<FLAGURL>flags/EUR.JPG</FLAGURL>
<ISO>EUR</ISO>
<NAME>Euro</NAME>
<COUNTRY>Euro Member Countries </COUNTRY>
<WEBUY>1.4146272457</WEBUY>
<WESELL>1.714971703</WESELL>
<INVBUY>0.7069</INVBUY>
<INVSELL>0.5831</INVSELL>
</RATE>
<RATE>
<ISFLAGGED>*</ISFLAGGED>
<FLAGURL>flags/GBP.JPG</FLAGURL>
<ISO>GBP</ISO>
<NAME>Pounds</NAME>
<COUNTRY>United Kingdom</COUNTRY>
<WEBUY>1.6196954972</WEBUY>
<WESELL>1.8691588785</WESELL>
<INVBUY>0.6174</INVBUY>
<INVSELL>0.535</INVSELL>
</RATE>
<RATE>
<ISFLAGGED>*</ISFLAGGED>
<FLAGURL>flags/NZD.JPG</FLAGURL>
<ISO>NZD</ISO>
<NAME>Dollars</NAME>
<COUNTRY>New Zealand</COUNTRY>
<WEBUY>0.8465250148</WEBUY>
<WESELL>0.9578544061</WESELL>
<INVBUY>1.1813</INVBUY>
<INVSELL>1.044</INVSELL>
</RATE>
<RATE>
<ISFLAGGED>*</ISFLAGGED>
<FLAGURL>flags/CAD.JPG</FLAGURL>
<ISO>CAD</ISO>
<NAME>Dollars</NAME>
<COUNTRY>Canada</COUNTRY>
<WEBUY>0.913576</WEBUY>
<WESELL>1.077935</WESELL>
<INVBUY>1.0946</INVBUY>
<INVSELL>0.9277</INVSELL>
</RATE>
<RATE>
<ISFLAGGED>*</ISFLAGGED>
<FLAGURL>flags/FJD.JPG</FLAGURL>
<ISO>FJD</ISO>
<NAME>Dollars</NAME>
<COUNTRY>Fiji</COUNTRY>
<WEBUY>0.5494505495</WEBUY>
<WESELL>0.7740537193</WESELL>
<INVBUY>1.82</INVBUY>
<INVSELL>1.2919</INVSELL>
</RATE>
<RATE>
<ISFLAGGED>*</ISFLAGGED>
<FLAGURL>flags/CNY.JPG</FLAGURL>
<ISO>CNY</ISO>
<NAME>Yuan Renminbi</NAME>
<COUNTRY>China</COUNTRY>
<WEBUY>0.170453577</WEBUY>
<WESELL>0.2070393375</WESELL>
<INVBUY>5.8667</INVBUY>
<INVSELL>4.83</INVSELL>
</RATE>
<RATE>
<ISFLAGGED>*</ISFLAGGED>
<FLAGURL>flags/HKD.JPG</FLAGURL>
<ISO>HKD</ISO>
<NAME>Dollars</NAME>
<COUNTRY>Hong Kong</COUNTRY>
<WEBUY>0.1377410468</WEBUY>
<WESELL>0.1736111111</WESELL>
<INVBUY>7.26</INVBUY>
<INVSELL>5.76</INVSELL>
</RATE>
<RATE>
<ISFLAGGED>*</ISFLAGGED>
<FLAGURL>flags/SGD.JPG</FLAGURL>
<ISO>SGD</ISO>
<NAME>Dollars</NAME>
<COUNTRY>Singapore</COUNTRY>
<WEBUY>0.8658008658</WEBUY>
<WESELL>1.0111223458</WESELL>
<INVBUY>1.155</INVBUY>
<INVSELL>0.989</INVSELL>
</RATE>
<RATE>
<ISFLAGGED>*</ISFLAGGED>
<FLAGURL>flags/THB.JPG</FLAGURL>
<ISO>THB</ISO>
<NAME>Baht</NAME>
<COUNTRY>Thailand</COUNTRY>
<WEBUY>0.0339443313</WEBUY>
<WESELL>0.0454545455</WESELL>
<INVBUY>29.46</INVBUY>
<INVSELL>22</INVSELL>
</RATE>
<RATE>
<ISFLAGGED>*</ISFLAGGED>
<FLAGURL>flags/CLP.JPG</FLAGURL>
<ISO>CLP</ISO>
<NAME>Pesos</NAME>
<COUNTRY>Chile</COUNTRY>
<WEBUY>0.00153</WEBUY>
<WESELL>0.00207</WESELL>
<INVBUY>653.5948</INVBUY>
<INVSELL>483.0918</INVSELL>
</RATE>
<RATE>
<ISFLAGGED>*</ISFLAGGED>
<FLAGURL>flags/DKK.JPG</FLAGURL>
<ISO>DKK</ISO>
<NAME>Kroner</NAME>
<COUNTRY>Denmark</COUNTRY>
<WEBUY>0.1813</WEBUY>
<WESELL>0.24528</WESELL>
<INVBUY>5.5158</INVBUY>
<INVSELL>4.0769</INVSELL>
</RATE>
<RATE>
<ISFLAGGED>*</ISFLAGGED>
<FLAGURL>flags/IDR.JPG</FLAGURL>
<ISO>IDR</ISO>
<NAME>Rupiahs</NAME>
<COUNTRY>Indonesia</COUNTRY>
<WEBUY>0.000072923503245</WEBUY>
<WESELL>0.000102239034864</WESELL>
<INVBUY>13713</INVBUY>
<INVSELL>9781</INVSELL>
</RATE>
<RATE>
<ISFLAGGED>*</ISFLAGGED>
<FLAGURL>flags/JPY.JPG</FLAGURL>
<ISO>JPY</ISO>
<NAME>Yen</NAME>
<COUNTRY>Japan</COUNTRY>
<WEBUY>0.0107032003</WEBUY>
<WESELL>0.012987013</WESELL>
<INVBUY>93.43</INVBUY>
<INVSELL>77</INVSELL>
</RATE>
<RATE>
<ISFLAGGED>*</ISFLAGGED>
<FLAGURL>flags/KRW.JPG</FLAGURL>
<ISO>KRW</ISO>
<NAME>Won</NAME>
<COUNTRY>Korea (South)</COUNTRY>
<WEBUY>0.0009592878</WEBUY>
<WESELL>0.0012738854</WESELL>
<INVBUY>1042.44</INVBUY>
<INVSELL>785</INVSELL>
</RATE>
<RATE>
<ISFLAGGED>*</ISFLAGGED>
<FLAGURL>flags/MYR.JPG</FLAGURL>
<ISO>MYR</ISO>
<NAME>Ringgits</NAME>
<COUNTRY>Malaysia</COUNTRY>
<WEBUY>0.2693602694</WEBUY>
<WESELL>0.3344481605</WESELL>
<INVBUY>3.7125</INVBUY>
<INVSELL>2.99</INVSELL>
</RATE>
<RATE>
<ISFLAGGED>*</ISFLAGGED>
<FLAGURL>flags/TRL.JPG</FLAGURL>
<ISO>TRL</ISO>
<NAME>Liras</NAME>
<COUNTRY>Turkey</COUNTRY>
<WEBUY>0.12873</WEBUY>
<WESELL>0.17777</WESELL>
<INVBUY>7.7682</INVBUY>
<INVSELL>5.6252</INVSELL>
</RATE>
</CATALOG>
