<?xml version="1.0" encoding="ISO-8859-1"?>
<?xml-stylesheet type="text/css" href="currency_table_widget.css"?>
<CATALOG>
<TIMESTAMP>Rates updated on 4/05/2016 at 15:06:16 </TIMESTAMP>

<RATE>
<ISFLAGGED>**</ISFLAGGED>
<FLAGURL>flags/USD.JPG</FLAGURL>
<ISO>USD</ISO>
<NAME>Dollars</NAME>
<COUNTRY>United States of America</COUNTRY>
<WEBUY>1.283697047497</WEBUY>
<WESELL>1.389081816919</WESELL>
<INVBUY>0.779</INVBUY>
<INVSELL>0.7199</INVSELL>
</RATE>
<RATE>
<ISFLAGGED>**</ISFLAGGED>
<FLAGURL>flags/GBP.JPG</FLAGURL>
<ISO>GBP</ISO>
<NAME>Pounds</NAME>
<COUNTRY>United Kingdom</COUNTRY>
<WEBUY>1.857010213556</WEBUY>
<WESELL>2.036245163918</WESELL>
<INVBUY>0.5385</INVBUY>
<INVSELL>0.4911</INVSELL>
</RATE>
<RATE>
<ISFLAGGED>**</ISFLAGGED>
<FLAGURL>flags/EUR.JPG</FLAGURL>
<ISO>EUR</ISO>
<NAME>Euro</NAME>
<COUNTRY>Euro Member Countries </COUNTRY>
<WEBUY>1.469939732471</WEBUY>
<WESELL>1.619957881095</WESELL>
<INVBUY>0.6803</INVBUY>
<INVSELL>0.6173</INVSELL>
</RATE>
</CATALOG>
