<?xml version="1.0" encoding="ISO-8859-1"?>
<?xml-stylesheet type="text/css" href="currency_table_widget.css"?>
<CATALOG>
<TIMESTAMP>Rates updated on 18/07/2020 at 21:52:20 Auckland</TIMESTAMP>

<RATE>
<ISFLAGGED>**</ISFLAGGED>
<FLAGURL>flags/USD.JPG</FLAGURL>
<ISO>USD</ISO>
<NAME>Dollars</NAME>
<COUNTRY>USD</COUNTRY>
<ID></ID>
<WEBUY>1.41801</WEBUY>
<WESELL>1.57048</WESELL>
<INVBUY>0.7052</INVBUY>
<INVSELL>0.6367</INVSELL>
</RATE>
<RATE>
<ISFLAGGED>*</ISFLAGGED>
<FLAGURL>flags/AUD.JPG</FLAGURL>
<ISO>AUD</ISO>
<NAME>Dollars</NAME>
<COUNTRY>Australia</COUNTRY>
<ID></ID>
<WEBUY>1.00224</WEBUY>
<WESELL>1.09553</WESELL>
<INVBUY>0.9978</INVBUY>
<INVSELL>0.9128</INVSELL>
</RATE>
<RATE>
<ISFLAGGED>*</ISFLAGGED>
<FLAGURL>flags/CAD.JPG</FLAGURL>
<ISO>CAD</ISO>
<NAME>Dollars</NAME>
<COUNTRY>Canada</COUNTRY>
<ID></ID>
<WEBUY>1.0554</WEBUY>
<WESELL>1.1677</WESELL>
<INVBUY>0.9475</INVBUY>
<INVSELL>0.8564</INVSELL>
</RATE>
<RATE>
<ISFLAGGED>*</ISFLAGGED>
<FLAGURL>flags/CNY.JPG</FLAGURL>
<ISO>CNY</ISO>
<NAME>Yuan Renminbi</NAME>
<COUNTRY>China</COUNTRY>
<ID></ID>
<WEBUY>0.196257</WEBUY>
<WESELL>0.228966</WESELL>
<INVBUY>5.095</INVBUY>
<INVSELL>4.367</INVSELL>
</RATE>
<RATE>
<ISFLAGGED>*</ISFLAGGED>
<FLAGURL>flags/EUR.JPG</FLAGURL>
<ISO>EUR</ISO>
<NAME>Euro</NAME>
<COUNTRY>Euro</COUNTRY>
<ID></ID>
<WEBUY>1.63791</WEBUY>
<WESELL>1.79473</WESELL>
<INVBUY>0.6105</INVBUY>
<INVSELL>0.5572</INVSELL>
</RATE>
<RATE>
<ISFLAGGED>*</ISFLAGGED>
<FLAGURL>flags/FJD.JPG</FLAGURL>
<ISO>FJD</ISO>
<NAME>Dollars</NAME>
<COUNTRY>Fiji</COUNTRY>
<ID></ID>
<WEBUY>0.67069</WEBUY>
<WESELL>0.73367</WESELL>
<INVBUY>1.491</INVBUY>
<INVSELL>1.363</INVSELL>
</RATE>
<RATE>
<ISFLAGGED>*</ISFLAGGED>
<FLAGURL>flags/GBP.JPG</FLAGURL>
<ISO>GBP</ISO>
<NAME>Pounds</NAME>
<COUNTRY>UK</COUNTRY>
<ID></ID>
<WEBUY>1.76274</WEBUY>
<WESELL>1.9735</WESELL>
<INVBUY>0.5673</INVBUY>
<INVSELL>0.5067</INVSELL>
</RATE>
<RATE>
<ISFLAGGED>*</ISFLAGGED>
<FLAGURL>flags/HKD.JPG</FLAGURL>
<ISO>HKD</ISO>
<NAME>Dollars</NAME>
<COUNTRY>HK</COUNTRY>
<ID></ID>
<WEBUY>0.18677</WEBUY>
<WESELL>0.2025</WESELL>
<INVBUY>5.3542</INVBUY>
<INVSELL>4.9383</INVSELL>
</RATE>
<RATE>
<ISFLAGGED>*</ISFLAGGED>
<FLAGURL>flags/IDR.JPG</FLAGURL>
<ISO>IDR</ISO>
<NAME>Rupiahs</NAME>
<COUNTRY>Indonesia</COUNTRY>
<ID></ID>
<WEBUY>0.000098635733</WEBUY>
<WESELL>0.0001142</WESELL>
<INVBUY>10138.31</INVBUY>
<INVSELL>8756.57</INVSELL>
</RATE>
<RATE>
<ISFLAGGED>*</ISFLAGGED>
<FLAGURL>flags/INR.JPG</FLAGURL>
<ISO>INR</ISO>
<NAME>Rupees</NAME>
<COUNTRY>India</COUNTRY>
<ID></ID>
<WEBUY>0.018721897181</WEBUY>
<WESELL>0.0211639</WESELL>
<INVBUY>53.4134</INVBUY>
<INVSELL>47.2503</INVSELL>
</RATE>
<RATE>
<ISFLAGGED>*</ISFLAGGED>
<FLAGURL>flags/JPY.JPG</FLAGURL>
<ISO>JPY</ISO>
<NAME>Yen</NAME>
<COUNTRY>Japan</COUNTRY>
<ID></ID>
<WEBUY>0.01332395</WEBUY>
<WESELL>0.0146065</WESELL>
<INVBUY>75.053</INVBUY>
<INVSELL>68.463</INVSELL>
</RATE>
<RATE>
<ISFLAGGED>*</ISFLAGGED>
<FLAGURL>flags/MYR.JPG</FLAGURL>
<ISO>MYR</ISO>
<NAME>Ringgits</NAME>
<COUNTRY>Malaysia</COUNTRY>
<ID></ID>
<WEBUY>0.33982</WEBUY>
<WESELL>0.40064</WESELL>
<INVBUY>2.9427</INVBUY>
<INVSELL>2.496</INVSELL>
</RATE>
<RATE>
<ISFLAGGED>*</ISFLAGGED>
<FLAGURL>flags/PHP.JPG</FLAGURL>
<ISO>PHP</ISO>
<NAME>Pesos</NAME>
<COUNTRY>Philippines</COUNTRY>
<ID></ID>
<WEBUY>0.0262497503</WEBUY>
<WESELL>0.0345879</WESELL>
<INVBUY>38.0956</INVBUY>
<INVSELL>28.9118</INVSELL>
</RATE>
<RATE>
<ISFLAGGED>*</ISFLAGGED>
<FLAGURL>flags/SGD.JPG</FLAGURL>
<ISO>SGD</ISO>
<NAME>Dollars</NAME>
<COUNTRY>Singapore</COUNTRY>
<ID></ID>
<WEBUY>1.03097</WEBUY>
<WESELL>1.14065</WESELL>
<INVBUY>0.97</INVBUY>
<INVSELL>0.8767</INVSELL>
</RATE>
<RATE>
<ISFLAGGED>*</ISFLAGGED>
<FLAGURL>flags/THB.JPG</FLAGURL>
<ISO>THB</ISO>
<NAME>Baht</NAME>
<COUNTRY>Thailand</COUNTRY>
<ID></ID>
<WEBUY>0.0443033588</WEBUY>
<WESELL>0.0539345</WESELL>
<INVBUY>22.5717</INVBUY>
<INVSELL>18.541</INVSELL>
</RATE>
<RATE>
<ISFLAGGED>*</ISFLAGGED>
<FLAGURL>flags/VND.JPG</FLAGURL>
<ISO>VND</ISO>
<NAME>Dong</NAME>
<COUNTRY>Viet Nam</COUNTRY>
<ID></ID>
<WEBUY>0.00006050102483974</WEBUY>
<WESELL>0.000071</WESELL>
<INVBUY>16528.6456</INVBUY>
<INVSELL>14084.507</INVSELL>
</RATE>
<RATE>
<ISFLAGGED>*</ISFLAGGED>
<FLAGURL>flags/ZAR.JPG</FLAGURL>
<ISO>ZAR</ISO>
<NAME>Rand</NAME>
<COUNTRY>SA</COUNTRY>
<ID></ID>
<WEBUY>0.08681</WEBUY>
<WESELL>0.09869</WESELL>
<INVBUY>11.5193</INVBUY>
<INVSELL>10.1327</INVSELL>
</RATE>
</CATALOG>
